twigs_ssl_audit/__init__.py
twigs_ssl_audit/twigs_ssl_audit.py
twigs_ssl_audit/ssl_audit/.travis.yml
twigs_ssl_audit/ssl_audit/LICENSE
twigs_ssl_audit/ssl_audit/op.json
twigs_ssl_audit/ssl_audit/testssl.sh
twigs_ssl_audit/ssl_audit/bin/OPENSSL-LICENSE.txt
twigs_ssl_audit/ssl_audit/bin/Readme.md
twigs_ssl_audit/ssl_audit/bin/fedora-dirk-ipv6.diff
twigs_ssl_audit/ssl_audit/bin/krb5-ciphers.txt
twigs_ssl_audit/ssl_audit/bin/new-ciphers.diffed2vanilla.txt
twigs_ssl_audit/ssl_audit/bin/new-ciphers.std_distro.txt
twigs_ssl_audit/ssl_audit/bin/openssl-Vall.krb.txt
twigs_ssl_audit/ssl_audit/bin/openssl-Vall.txt
twigs_ssl_audit/ssl_audit/bin/openssl.Darwin.x86_64
twigs_ssl_audit/ssl_audit/bin/openssl.FreeBSD.amd64
twigs_ssl_audit/ssl_audit/bin/openssl.Linux.i686
twigs_ssl_audit/ssl_audit/bin/openssl.Linux.x86_64
twigs_ssl_audit/ssl_audit/bin/openssl.Linux.x86_64.krb
twigs_ssl_audit/ssl_audit/etc/Apple.pem
twigs_ssl_audit/ssl_audit/etc/Java.pem
twigs_ssl_audit/ssl_audit/etc/Linux.pem
twigs_ssl_audit/ssl_audit/etc/Microsoft.pem
twigs_ssl_audit/ssl_audit/etc/Mozilla.pem
twigs_ssl_audit/ssl_audit/etc/README.md
twigs_ssl_audit/ssl_audit/etc/ca_hashes.txt
twigs_ssl_audit/ssl_audit/etc/cipher-mapping.txt
twigs_ssl_audit/ssl_audit/etc/client-simulation.txt
twigs_ssl_audit/ssl_audit/etc/client-simulation.wiresharked.md
twigs_ssl_audit/ssl_audit/etc/client-simulation.wiresharked.txt
twigs_ssl_audit/ssl_audit/etc/common-primes.txt
twigs_ssl_audit/ssl_audit/etc/curves.txt
twigs_ssl_audit/ssl_audit/etc/tls_data.txt
twigs_ssl_audit/ssl_audit/t/00_testssl_help.t
twigs_ssl_audit/ssl_audit/t/01_testssl_banner.t
twigs_ssl_audit/ssl_audit/t/02_clientsim_txt_parsable.t
twigs_ssl_audit/ssl_audit/t/05_ca_hashes_up_to_date.t
twigs_ssl_audit/ssl_audit/t/07_isJSON_valid.t
twigs_ssl_audit/ssl_audit/t/08_isHTML_valid.t
twigs_ssl_audit/ssl_audit/t/09_isJSON_severitylevel_valid.t
twigs_ssl_audit/ssl_audit/t/20_baseline_ipv4_http.t
twigs_ssl_audit/ssl_audit/t/21_baseline_ipv6_http.t.DISABLED
twigs_ssl_audit-1.0.2.dist-info/AUTHORS.rst
twigs_ssl_audit-1.0.2.dist-info/LICENSE
twigs_ssl_audit-1.0.2.dist-info/METADATA
twigs_ssl_audit-1.0.2.dist-info/WHEEL
twigs_ssl_audit-1.0.2.dist-info/top_level.txt
twigs_ssl_audit-1.0.2.dist-info/RECORD
