Metadata-Version: 2.1
Name: twigs-ssl-audit
Version: 1.0.2
Summary: TWIGS SSL Audit
Home-page: https://github.com/threatwatch/twigs_ssl_audit
Author: Paresh Borkar
Author-email: opensource@threatwatch.io
License: GNU General Public License v3
Keywords: twigs_ssl_audit
Platform: UNKNOWN
Classifier: Development Status :: 2 - Pre-Alpha
Classifier: Intended Audience :: Developers
Classifier: License :: OSI Approved :: GNU General Public License v3 (GPLv3)
Classifier: Natural Language :: English
Classifier: Programming Language :: Python :: 2
Classifier: Programming Language :: Python :: 2.7
Classifier: Programming Language :: Python :: 3
Classifier: Programming Language :: Python :: 3.4
Classifier: Programming Language :: Python :: 3.5
Classifier: Programming Language :: Python :: 3.6
Classifier: Programming Language :: Python :: 3.7
